ck_demos/all_demos.py
ck_demos/__init__.py
ck_demos/dataset/demo_dataset_from_sampler.py
ck_demos/dataset/__init__.py
ck_demos/dataset/demo_dataset_builder.py
ck_demos/learning/__init__.py
ck_demos/learning/demo_simple_learning.py
ck_demos/learning/demo_bayesian_network_from_cross_tables.py
ck_demos/circuit/__init__.py
ck_demos/circuit/demo_derivatives.py
ck_demos/circuit/demo_circuit_dump.py
ck_demos/sampling/demo_uniform_sampler.py
ck_demos/sampling/check_sampler.py
ck_demos/sampling/demo_wmc_direct_sampler.py
ck_demos/sampling/__init__.py
ck_demos/sampling/demo_marginal_direct_sampler.py
ck_demos/utils/__init__.py
ck_demos/utils/stop_watch.py
ck_demos/utils/sample_model.py
ck_demos/utils/convert_network.py
ck_demos/utils/compare.py
ck_demos/programs/demo_program_none.py
ck_demos/programs/demo_program_buffer.py
ck_demos/programs/demo_program_multi.py
ck_demos/programs/demo_raw_program_dump.py
ck_demos/programs/demo_raw_program_llvm.py
ck_demos/programs/__init__.py
ck_demos/programs/demo_raw_program_interpreted.py
ck_demos/programs/demo_program_single.py
ck_demos/pgm_compiler/demo_recursive_conditioning.py
ck_demos/pgm_compiler/demo_join_tree.py
ck_demos/pgm_compiler/demo_variable_elimination.py
ck_demos/pgm_compiler/demo_wmc_program.py
ck_demos/pgm_compiler/compare_pgm_compilers.py
ck_demos/pgm_compiler/demo_marginals_program.py
ck_demos/pgm_compiler/__init__.py
ck_demos/pgm_compiler/time_fe_compiler.py
ck_demos/pgm_compiler/demo_factor_elimination.py
ck_demos/pgm_compiler/demo_pgm_compiler.py
ck_demos/pgm_compiler/demo_compiler_dump.py
ck_demos/pgm_compiler/demo_mpe_program.py
ck_demos/circuit_compiler/compare_circuit_compilers.py
ck_demos/circuit_compiler/__init__.py
ck_demos/circuit_compiler/show_llvm_program.py
ck_demos/ace/demo_ace.py
ck_demos/ace/__init__.py
ck_demos/ace/copy_ace_to_ck.py
ck_demos/ace/simple_ace_demo.py
ck_demos/pgm/show_examples.py
ck_demos/pgm/__init__.py
compiled_knowledge-4.2.1.dist-info/RECORD
compiled_knowledge-4.2.1.dist-info/WHEEL
compiled_knowledge-4.2.1.dist-info/top_level.txt
compiled_knowledge-4.2.1.dist-info/METADATA
compiled_knowledge-4.2.1.dist-info/licenses/LICENSE.txt
