Metadata-Version: 2.4
Name: compiled-knowledge
Version: 4.2.1
Summary: A Python package for compiling and querying discrete probabilistic graphical models.
Author-email: Barry Drake <barry@compiledknowledge.org>
License-Expression: MIT
Project-URL: Homepage, https://github.com/ropeless/compiled_knowledge
Project-URL: Issues, https://github.com/ropeless/compiled_knowledge/issues
Classifier: Programming Language :: Python :: 3
Classifier: Operating System :: OS Independent
Requires-Python: >=3.12
License-File: LICENSE.txt
Requires-Dist: llvmlite
Requires-Dist: numpy
Requires-Dist: scipy
Dynamic: license-file
